gpass/__init__.py
gpass-2.1.0.dist-info/LICENSE
gpass-2.1.0.dist-info/METADATA
gpass-2.1.0.dist-info/WHEEL
gpass-2.1.0.dist-info/top_level.txt
gpass-2.1.0.dist-info/RECORD
