Metadata-Version: 2.1
Name: gpass
Version: 2.1.0
Summary: A flexible and easy to use, terminal based password input utility
Home-page: https://gitlab.com/loggerheads-with-binary/gpass/
Author: Anna Aniruddh Radhakrishnan
Author-email: dev@aniruddh.ml
License: UNKNOWN
Download-URL: http://pypi.python.org/pypi/gpass
Project-URL: Documentation, https://gitlab.com/loggerheads-with-binary/gpass/README.md
Project-URL: Source, https://gitlab.com/loggerheads-with-binary/gpass/
Project-URL: Tracker, https://gitlab.com/loggerheads-with-binary/gpass/issues
Platform: UNKNOWN
Classifier: Operating System :: OS Independent
Classifier: Environment :: Console
Classifier: Intended Audience :: Developers
Classifier: Intended Audience :: System Administrators
Classifier: License :: OSI Approved :: MIT License
Classifier: Programming Language :: Python :: 3
Classifier: Natural Language :: English
Classifier: Topic :: Security :: Cryptography
License-File: LICENSE
Requires-Dist: colorama
Requires-Dist: termcolor
